<?xml version="1.0" encoding="UTF-8"?>
<!DOCTYPE struts PUBLIC
    "-//Apache Software Foundation//DTD Struts Configuration 2.5//EN"
    "http://struts.apache.org/dtds/struts-2.5.dtd">

<struts>
    <!-- Define a namespace for the package -->
    <package name="default" namespace="/pets" extends="struts-default">
        <action name="adddetails" class="com.actions.adddetails" method="create">
            <result name="success">/success.jsp</result>
            <result name="error">/error.jsp</result>
        </action>
    </package>
</struts>
